lynxkite_graph_analytics/__init__.py
lynxkite_graph_analytics/core.py
lynxkite_graph_analytics/lynxkite_ops.py
lynxkite_graph_analytics/ml_ops.py
lynxkite_graph_analytics/networkx_ops.py
lynxkite_graph_analytics/pykeen_ops.py
lynxkite_graph_analytics/pytorch/__init__.py
lynxkite_graph_analytics/pytorch/pytorch_core.py
lynxkite_graph_analytics/pytorch/pytorch_ops.py
lynxkite_graph_analytics-0.3.0.dist-info/WHEEL
lynxkite_graph_analytics-0.3.0.dist-info/METADATA
lynxkite_graph_analytics-0.3.0.dist-info/RECORD
